{
"Version": "0.7.21.0",
"Object": {
"$type": "RogueEssence.Data.TileData, RogueEssence",
"Name": {
"DefaultText": "Mirage Tablet",
"LocalTexts": {
"de": "Trugbild-Tafel",
"zh-hans": "幻象石板"
}
},
"Desc": {
"DefaultText": "A stone tablet engraved with a set of names. There is an indent at the bottom that fits an Explorer Badge...",
"LocalTexts": {
"de": "Eine Steintafel mit einigen eingravierten Namen. Auf der Unterseite ist eine Einkerbung, in die ein Erkunderorden hineinpasst...",
"zh-hans": "一块石板，上面刻着一组名字。底部有一个凹槽，正好可以嵌入探险队徽章……"
}
},
"Released": true,
"Comment": "",
"Anim": {
"AnimIndex": "Tile_Signal",
"FrameTime": 12,
"StartFrame": -1,
"EndFrame": -1,
"AnimDir": -1,
"Alpha": 255,
"AnimFlip": 0
},
"Offset": {
"X": 0,
"Y": 0
},
"Layer": 0,
"BlockItem": true,
"StepType": 1,
"MinimapIcon": {
"X": 4,
"Y": 1
},
"MinimapColor": "0, 255, 255, 255",
"LandedOnTiles": [
{
"Key": {
"str": [
0
]
},
"Value": {
"$type": "PMDC.Dungeon.TriggerUnderfootEvent, PMDC"
}
}
],
"InteractWithTiles": [
{
"Key": {
"str": [
0
]
},
"Value": {
"$type": "PMDC.Dungeon.LeaderCharEvent, PMDC",
"BaseEvent": {
"$type": "PMDC.Dungeon.LockdownTileEvent, PMDC",
"CheckClearStatus": "map_clear_check"
}
}
},
{
"Key": {
"str": [
0
]
},
"Value": {
"$type": "PMDC.Dungeon.LeaderCharEvent, PMDC",
"BaseEvent": {
"$type": "PMDC.Dungeon.BossSpawnEvent, PMDC"
}
}
}
]
}
}