{
"Version": "0.7.24.0",
"Object": {
"$type": "RogueEssence.Data.SkillData, RogueEssence",
"Name": {
"DefaultText": "Leafage",
"LocalTexts": {
"fr": "Feuillage",
"de": "Blattwerk",
"es": "Follaje",
"it": "Fogliame",
"ko": "나뭇잎",
"ja": "このは",
"ja-jp": "このは",
"zh-hans": "树叶",
"zh-hant": "樹葉"
}
},
"Desc": {
"DefaultText": "The user attacks by pelting the target with leaves.",
"LocalTexts": {
"fr": "Le lanceur attaque l'ennemi avec des feuilles.",
"de": "Der Anwender greift das Ziel mit Blättern an.",
"es": "Ataca al oponente lanzando hojas.",
"it": "Attacca il bersaglio con delle foglie.",
"ko": "잎을 상대에 맞춰 공격한다.",
"ja": "はっぱを　あいてに　あてて こうげきする。",
"ja-jp": "はっぱを　相手に　当てて 攻撃する。",
"zh-hans": "将叶片打向对手，进行攻击。",
"zh-hant": "將葉片打向對手， 進行攻擊。"
}
},
"Released": true,
"Comment": "",
"IndexNum": 670,
"BaseCharges": 19,
"Strikes": 1,
"HitboxAction": {
"$type": "RogueEssence.Dungeon.ThrowAction, RogueEssence",
"Anim": {
"AnimIndex": "Leaf_Storm_Hit_Mark",
"FrameTime": 1,
"StartFrame": -1,
"EndFrame": -1,
"AnimDir": -1,
"Alpha": 255,
"AnimFlip": 0
},
"Emitter": {
"$type": "RogueEssence.Content.EmptyAttachEmitter, RogueEssence"
},
"Range": 2,
"Speed": 8,
"Coverage": 2,
"ItemSprite": "",
"CharAnimData": {
"$type": "RogueEssence.Dungeon.CharAnimFrameType, RogueEssence",
"ActionType": 7
},
"TargetAlignments": 4,
"TileEmitter": {
"$type": "RogueEssence.Content.EmptyFiniteEmitter, RogueEssence",
"LocHeight": 0
},
"PreActions": [],
"ActionFX": {
"Delay": 0,
"Sound": "_UNK_DUN_Sneeze",
"Emitter": {
"$type": "RogueEssence.Content.EmptyFiniteEmitter, RogueEssence",
"LocHeight": 0
},
"ScreenMovement": {
"MinShake": 0,
"MaxShake": 0,
"MaxShakeTime": 0
}
},
"LagBehindTime": 0
},
"Explosion": {
"TargetAlignments": 4,
"HitTiles": false,
"Range": 0,
"Speed": 0,
"TileEmitter": {
"$type": "RogueEssence.Content.EmptyFiniteEmitter, RogueEssence",
"LocHeight": 0
},
"Emitter": {
"$type": "RogueEssence.Content.EmptyCircleSquareEmitter, RogueEssence",
"LocHeight": 0
},
"IntroFX": [],
"ExplodeFX": {
"Delay": 0,
"Sound": "",
"Emitter": {
"$type": "RogueEssence.Content.EmptyFiniteEmitter, RogueEssence",
"LocHeight": 0
},
"ScreenMovement": {
"MinShake": 0,
"MaxShake": 0,
"MaxShakeTime": 0
}
}
},
"Data": {
"Element": "grass",
"Category": 1,
"HitRate": 100,
"SkillStates": [
{
"$type": "RogueEssence.Dungeon.BasePowerState, RogueEssence",
"Power": 40
}
],
"BeforeTryActions": [],
"BeforeActions": [],
"OnActions": [],
"BeforeExplosions": [],
"BeforeHits": [],
"OnHits": [
{
"Key": {
"str": [
-1
]
},
"Value": {
"$type": "PMDC.Dungeon.DamageFormulaEvent, PMDC"
}
}
],
"OnHitTiles": [],
"AfterActions": [],
"ElementEffects": [],
"IntroFX": [],
"HitFX": {
"Delay": 0,
"Sound": "_UNK_DUN_Rustle_2",
"Emitter": {
"$type": "RogueEssence.Content.SingleEmitter, RogueEssence",
"LocHeight": 20,
"finished": false,
"Offset": 0,
"Anim": {
"$type": "RogueEssence.Content.StaticAnim, RogueEssence",
"Anim": {
"AnimIndex": "Razor_Leaf_Charge",
"FrameTime": 2,
"StartFrame": -1,
"EndFrame": -1,
"AnimDir": -1,
"Alpha": 255,
"AnimFlip": 0
},
"TotalTime": 0,
"Cycles": 1,
"FrameOffset": 0
},
"Layer": 2,
"UseDest": false
},
"ScreenMovement": {
"MinShake": 0,
"MaxShake": 0,
"MaxShakeTime": 0
}
},
"HitCharAction": {
"$type": "RogueEssence.Dungeon.CharAnimProcess, RogueEssence",
"Process": 0,
"AnimOverride": 0
}
}
}
}