{
"Version": "0.7.20.0",
"Object": {
"$type": "RogueEssence.Data.MonsterData, RogueEssence",
"Name": {
"DefaultText": "Accelgor",
"LocalTexts": {
"ja": "アギルダー",
"ko": "어지리더",
"zh-hant": "敏捷蟲",
"fr": "Limaspeed",
"de": "Hydragil",
"es": "Accelgor",
"it": "Accelgor",
"ja-jp": "アギルダー",
"zh-hans": "敏捷虫"
}
},
"Released": false,
"Comment": "",
"Title": {
"DefaultText": "Shell Out Pokémon",
"LocalTexts": {
"ja": "からぬけポケモン",
"ko": "탈껍질포켓몬",
"zh-hant": "脫殼寶可夢",
"fr": "Pokémon Exuviateur",
"de": "Entschalungs-Pokémon",
"es": "Pokémon Sincaparazón",
"it": "Pokémon Sgusciato",
"ja-jp": "からぬけポケモン",
"zh-hans": "脱壳宝可梦"
}
},
"IndexNum": 617,
"EXPTable": "medium_fast",
"SkillGroup1": "bug",
"SkillGroup2": "",
"JoinRate": -25,
"PromoteFrom": "shelmet",
"Promotions": [],
"Forms": [
{
"$type": "PMDC.Data.MonsterFormData, PMDC",
"Released": false,
"Generation": 6,
"GenderlessWeight": 2,
"MaleWeight": 4,
"FemaleWeight": 4,
"BaseHP": 80,
"BaseAtk": 70,
"BaseDef": 40,
"BaseMAtk": 100,
"BaseMDef": 60,
"BaseSpeed": 145,
"ExpYield": 173,
"Height": 0.8,
"Weight": 25.3,
"Personalities": [
31
],
"TeachSkills": [
{
"Skill": "hyper_beam"
},
{
"Skill": "toxic"
},
{
"Skill": "double_team"
},
{
"Skill": "rest"
},
{
"Skill": "substitute"
},
{
"Skill": "protect"
},
{
"Skill": "sludge_bomb"
},
{
"Skill": "sandstorm"
},
{
"Skill": "swagger"
},
{
"Skill": "attract"
},
{
"Skill": "return"
},
{
"Skill": "frustration"
},
{
"Skill": "hidden_power"
},
{
"Skill": "rain_dance"
},
{
"Skill": "facade"
},
{
"Skill": "u_turn"
},
{
"Skill": "focus_blast"
},
{
"Skill": "energy_ball"
},
{
"Skill": "giga_impact"
},
{
"Skill": "venoshock"
},
{
"Skill": "round"
},
{
"Skill": "struggle_bug"
},
{
"Skill": "sleep_talk"
},
{
"Skill": "confide"
},
{
"Skill": "infestation"
},
{
"Skill": "secret_power"
}
],
"SharedSkills": [],
"SecretSkills": [
{
"Skill": "snore"
},
{
"Skill": "giga_drain"
},
{
"Skill": "sleep_talk"
},
{
"Skill": "knock_off"
},
{
"Skill": "signal_beam"
},
{
"Skill": "gastro_acid"
},
{
"Skill": "bug_bite"
}
],
"FormName": {
"DefaultText": "Accelgor",
"LocalTexts": {
"ja": "アギルダー",
"ko": "어지리더",
"zh-hant": "敏捷蟲",
"fr": "Limaspeed",
"de": "Hydragil",
"es": "Accelgor",
"it": "Accelgor",
"ja-jp": "アギルダー",
"zh-hans": "敏捷虫"
}
},
"Temporary": false,
"PromoteForm": 0,
"Element1": "bug",
"Element2": "none",
"Intrinsic1": "hydration",
"Intrinsic2": "sticky_hold",
"Intrinsic3": "unburden",
"LevelSkills": [
{
"Level": 1,
"Skill": "water_shuriken"
},
{
"Level": 1,
"Skill": "final_gambit"
},
{
"Level": 1,
"Skill": "power_swap"
},
{
"Level": 1,
"Skill": "leech_life"
},
{
"Level": 1,
"Skill": "acid_spray"
},
{
"Level": 1,
"Skill": "double_team"
},
{
"Level": 1,
"Skill": "quick_attack"
},
{
"Level": 4,
"Skill": "acid_spray"
},
{
"Level": 8,
"Skill": "double_team"
},
{
"Level": 13,
"Skill": "quick_attack"
},
{
"Level": 16,
"Skill": "struggle_bug"
},
{
"Level": 20,
"Skill": "mega_drain"
},
{
"Level": 25,
"Skill": "swift"
},
{
"Level": 28,
"Skill": "me_first"
},
{
"Level": 32,
"Skill": "agility"
},
{
"Level": 37,
"Skill": "giga_drain"
},
{
"Level": 40,
"Skill": "u_turn"
},
{
"Level": 44,
"Skill": "bug_buzz"
},
{
"Level": 49,
"Skill": "recover"
},
{
"Level": 52,
"Skill": "power_swap"
},
{
"Level": 56,
"Skill": "final_gambit"
}
]
}
]
}
}