{
"Version": "0.7.20.0",
"Object": {
"$type": "RogueEssence.Data.MonsterData, RogueEssence",
"Name": {
"DefaultText": "Altaria",
"LocalTexts": {
"ja": "チルタリス",
"ko": "파비코리",
"zh-hant": "七夕青鳥",
"fr": "Altaria",
"de": "Altaria",
"es": "Altaria",
"it": "Altaria",
"ja-jp": "チルタリス",
"zh-hans": "七夕青鸟"
}
},
"Released": true,
"Comment": "",
"Title": {
"DefaultText": "Humming Pokémon",
"LocalTexts": {
"ja": "ハミングポケモン",
"ko": "허밍포켓몬",
"zh-hant": "哼唱寶可夢",
"fr": "Pokémon Virevolteur",
"de": "Summsel-Pokémon",
"es": "Pokémon Cantor",
"it": "Pokémon Canterino",
"ja-jp": "ハミングポケモン",
"zh-hans": "哼唱宝可梦"
}
},
"IndexNum": 334,
"EXPTable": "erratic",
"SkillGroup1": "flying",
"SkillGroup2": "dragon",
"JoinRate": -30,
"PromoteFrom": "swablu",
"Promotions": [],
"Forms": [
{
"$type": "PMDC.Data.MonsterFormData, PMDC",
"Released": true,
"Generation": 6,
"GenderlessWeight": 2,
"MaleWeight": 4,
"FemaleWeight": 4,
"BaseHP": 75,
"BaseAtk": 70,
"BaseDef": 90,
"BaseMAtk": 70,
"BaseMDef": 105,
"BaseSpeed": 80,
"ExpYield": 172,
"Height": 1.1,
"Weight": 20.6,
"Personalities": [
0,
1,
2,
3,
4,
7,
9,
13,
14,
15,
16,
26,
29,
31,
36
],
"TeachSkills": [
{
"Skill": "fly"
},
{
"Skill": "roar"
},
{
"Skill": "flamethrower"
},
{
"Skill": "ice_beam"
},
{
"Skill": "hyper_beam"
},
{
"Skill": "solar_beam"
},
{
"Skill": "earthquake"
},
{
"Skill": "toxic"
},
{
"Skill": "double_team"
},
{
"Skill": "fire_blast"
},
{
"Skill": "rest"
},
{
"Skill": "thief"
},
{
"Skill": "protect"
},
{
"Skill": "steel_wing"
},
{
"Skill": "attract"
},
{
"Skill": "return"
},
{
"Skill": "frustration"
},
{
"Skill": "safeguard"
},
{
"Skill": "iron_tail"
},
{
"Skill": "hidden_power"
},
{
"Skill": "rain_dance"
},
{
"Skill": "sunny_day"
},
{
"Skill": "rock_smash"
},
{
"Skill": "facade"
},
{
"Skill": "secret_power"
},
{
"Skill": "aerial_ace"
},
{
"Skill": "dragon_claw"
},
{
"Skill": "dream_eater"
},
{
"Skill": "substitute"
},
{
"Skill": "endure"
},
{
"Skill": "swagger"
},
{
"Skill": "sleep_talk"
},
{
"Skill": "psych_up"
},
{
"Skill": "roost"
},
{
"Skill": "natural_gift"
},
{
"Skill": "pluck"
},
{
"Skill": "dragon_pulse"
},
{
"Skill": "giga_impact"
},
{
"Skill": "captivate"
},
{
"Skill": "hone_claws"
},
{
"Skill": "round"
},
{
"Skill": "echoed_voice"
},
{
"Skill": "incinerate"
},
{
"Skill": "bulldoze"
},
{
"Skill": "confide"
},
{
"Skill": "dazzling_gleam"
}
],
"SharedSkills": [],
"SecretSkills": [
{
"Skill": "body_slam"
},
{
"Skill": "double_edge"
},
{
"Skill": "mimic"
},
{
"Skill": "swift"
},
{
"Skill": "dream_eater"
},
{
"Skill": "substitute"
},
{
"Skill": "snore"
},
{
"Skill": "mud_slap"
},
{
"Skill": "endure"
},
{
"Skill": "swagger"
},
{
"Skill": "sleep_talk"
},
{
"Skill": "psych_up"
},
{
"Skill": "draco_meteor"
},
{
"Skill": "outrage"
},
{
"Skill": "twister"
},
{
"Skill": "uproar"
},
{
"Skill": "heat_wave"
},
{
"Skill": "air_cutter"
},
{
"Skill": "ominous_wind"
},
{
"Skill": "sky_attack"
},
{
"Skill": "heal_bell"
},
{
"Skill": "tailwind"
},
{
"Skill": "iron_tail"
},
{
"Skill": "hyper_voice"
},
{
"Skill": "roost"
},
{
"Skill": "dragon_pulse"
},
{
"Skill": "wonder_room"
}
],
"FormName": {
"DefaultText": "Altaria",
"LocalTexts": {
"ja": "チルタリス",
"ko": "파비코리",
"zh-hant": "七夕青鳥",
"fr": "Altaria",
"de": "Altaria",
"es": "Altaria",
"it": "Altaria",
"ja-jp": "チルタリス",
"zh-hans": "七夕青鸟"
}
},
"Temporary": false,
"PromoteForm": 0,
"Element1": "dragon",
"Element2": "flying",
"Intrinsic1": "natural_cure",
"Intrinsic2": "none",
"Intrinsic3": "cloud_nine",
"LevelSkills": [
{
"Level": 1,
"Skill": "sky_attack"
},
{
"Level": 1,
"Skill": "pluck"
},
{
"Level": 1,
"Skill": "peck"
},
{
"Level": 1,
"Skill": "growl"
},
{
"Level": 1,
"Skill": "astonish"
},
{
"Level": 1,
"Skill": "sing"
},
{
"Level": 3,
"Skill": "astonish"
},
{
"Level": 5,
"Skill": "sing"
},
{
"Level": 7,
"Skill": "fury_attack"
},
{
"Level": 9,
"Skill": "safeguard"
},
{
"Level": 11,
"Skill": "disarming_voice"
},
{
"Level": 14,
"Skill": "mist"
},
{
"Level": 17,
"Skill": "round"
},
{
"Level": 20,
"Skill": "natural_gift"
},
{
"Level": 23,
"Skill": "take_down"
},
{
"Level": 26,
"Skill": "refresh"
},
{
"Level": 30,
"Skill": "dragon_dance"
},
{
"Level": 34,
"Skill": "cotton_guard"
},
{
"Level": 35,
"Skill": "dragon_breath"
},
{
"Level": 40,
"Skill": "dragon_pulse"
},
{
"Level": 46,
"Skill": "perish_song"
},
{
"Level": 52,
"Skill": "moonblast"
},
{
"Level": 59,
"Skill": "sky_attack"
}
]
},
{
"$type": "PMDC.Data.MonsterFormData, PMDC",
"Released": false,
"Generation": 6,
"GenderlessWeight": 2,
"MaleWeight": 4,
"FemaleWeight": 4,
"BaseHP": 75,
"BaseAtk": 110,
"BaseDef": 110,
"BaseMAtk": 110,
"BaseMDef": 105,
"BaseSpeed": 80,
"ExpYield": 207,
"Height": 1.5,
"Weight": 20.6,
"Personalities": [
0,
1,
2,
3,
4,
7,
9,
13,
14,
15,
16,
26,
29,
31,
36
],
"TeachSkills": [
{
"Skill": "fly"
},
{
"Skill": "roar"
},
{
"Skill": "flamethrower"
},
{
"Skill": "ice_beam"
},
{
"Skill": "hyper_beam"
},
{
"Skill": "solar_beam"
},
{
"Skill": "earthquake"
},
{
"Skill": "toxic"
},
{
"Skill": "double_team"
},
{
"Skill": "fire_blast"
},
{
"Skill": "dream_eater"
},
{
"Skill": "rest"
},
{
"Skill": "substitute"
},
{
"Skill": "thief"
},
{
"Skill": "protect"
},
{
"Skill": "swagger"
},
{
"Skill": "steel_wing"
},
{
"Skill": "attract"
},
{
"Skill": "sleep_talk"
},
{
"Skill": "return"
},
{
"Skill": "frustration"
},
{
"Skill": "safeguard"
},
{
"Skill": "hidden_power"
},
{
"Skill": "rain_dance"
},
{
"Skill": "sunny_day"
},
{
"Skill": "psych_up"
},
{
"Skill": "rock_smash"
},
{
"Skill": "facade"
},
{
"Skill": "secret_power"
},
{
"Skill": "aerial_ace"
},
{
"Skill": "dragon_claw"
},
{
"Skill": "roost"
},
{
"Skill": "giga_impact"
},
{
"Skill": "hone_claws"
},
{
"Skill": "round"
},
{
"Skill": "echoed_voice"
},
{
"Skill": "incinerate"
},
{
"Skill": "bulldoze"
},
{
"Skill": "confide"
},
{
"Skill": "dazzling_gleam"
}
],
"SharedSkills": [],
"SecretSkills": [
{
"Skill": "sky_attack"
},
{
"Skill": "snore"
},
{
"Skill": "outrage"
},
{
"Skill": "heal_bell"
},
{
"Skill": "iron_tail"
},
{
"Skill": "uproar"
},
{
"Skill": "heat_wave"
},
{
"Skill": "hyper_voice"
},
{
"Skill": "tailwind"
},
{
"Skill": "dragon_pulse"
},
{
"Skill": "draco_meteor"
},
{
"Skill": "wonder_room"
}
],
"FormName": {
"DefaultText": "Mega Altaria",
"LocalTexts": {
"ja": "",
"ko": "",
"zh-hant": "",
"fr": "Méga-Altaria",
"de": "Mega-Altaria",
"es": "",
"it": "",
"ja-jp": "",
"zh-hans": ""
}
},
"Temporary": true,
"PromoteForm": 0,
"Element1": "dragon",
"Element2": "fairy",
"Intrinsic1": "pixilate",
"Intrinsic2": "none",
"Intrinsic3": "none",
"LevelSkills": [
{
"Level": 1,
"Skill": "sky_attack"
},
{
"Level": 1,
"Skill": "pluck"
},
{
"Level": 1,
"Skill": "peck"
},
{
"Level": 1,
"Skill": "growl"
},
{
"Level": 1,
"Skill": "astonish"
},
{
"Level": 1,
"Skill": "sing"
},
{
"Level": 3,
"Skill": "astonish"
},
{
"Level": 5,
"Skill": "sing"
},
{
"Level": 7,
"Skill": "fury_attack"
},
{
"Level": 9,
"Skill": "safeguard"
},
{
"Level": 11,
"Skill": "disarming_voice"
},
{
"Level": 14,
"Skill": "mist"
},
{
"Level": 17,
"Skill": "round"
},
{
"Level": 20,
"Skill": "natural_gift"
},
{
"Level": 23,
"Skill": "take_down"
},
{
"Level": 26,
"Skill": "refresh"
},
{
"Level": 30,
"Skill": "dragon_dance"
},
{
"Level": 34,
"Skill": "cotton_guard"
},
{
"Level": 35,
"Skill": "dragon_breath"
},
{
"Level": 40,
"Skill": "dragon_pulse"
},
{
"Level": 46,
"Skill": "perish_song"
},
{
"Level": 52,
"Skill": "moonblast"
},
{
"Level": 59,
"Skill": "sky_attack"
}
]
}
]
}
}