{
"Version": "0.7.20.0",
"Object": {
"$type": "RogueEssence.Data.MonsterData, RogueEssence",
"Name": {
"DefaultText": "Araquanid",
"LocalTexts": {
"ja": "オニシズクモ",
"ko": "깨비물거미",
"zh-hant": "滴蛛霸",
"fr": "Tarenbulle",
"de": "Aranestro",
"es": "Araquanid",
"it": "Araquanid",
"ja-jp": "オニシズクモ",
"zh-hans": "滴蛛霸"
}
},
"Released": false,
"Comment": "",
"Title": {
"DefaultText": "Water Bubble Pokémon",
"LocalTexts": {
"ja": "すいほうポケモン",
"ko": "수포포켓몬",
"zh-hant": "水泡寶可夢",
"fr": "Pokémon Aquabulle",
"de": "Wasserblasen-Pokémon",
"es": "Pokémon Pompa",
"it": "Pokémon Bolladacqua",
"ja-jp": "すいほうポケモン",
"zh-hans": "水泡宝可梦"
}
},
"IndexNum": 752,
"EXPTable": "medium_fast",
"SkillGroup1": "water_1",
"SkillGroup2": "bug",
"JoinRate": -15,
"PromoteFrom": "dewpider",
"Promotions": [],
"Forms": [
{
"$type": "PMDC.Data.MonsterFormData, PMDC",
"Released": false,
"Generation": 7,
"GenderlessWeight": 2,
"MaleWeight": 4,
"FemaleWeight": 4,
"BaseHP": 68,
"BaseAtk": 70,
"BaseDef": 92,
"BaseMAtk": 50,
"BaseMDef": 132,
"BaseSpeed": 42,
"ExpYield": 159,
"Height": 1.8,
"Weight": 82.0,
"Personalities": [
31
],
"TeachSkills": [
{
"Skill": "surf"
},
{
"Skill": "ice_beam"
},
{
"Skill": "blizzard"
},
{
"Skill": "toxic"
},
{
"Skill": "double_team"
},
{
"Skill": "reflect"
},
{
"Skill": "waterfall"
},
{
"Skill": "leech_life"
},
{
"Skill": "rest"
},
{
"Skill": "substitute"
},
{
"Skill": "protect"
},
{
"Skill": "swagger"
},
{
"Skill": "attract"
},
{
"Skill": "sleep_talk"
},
{
"Skill": "return"
},
{
"Skill": "frustration"
},
{
"Skill": "safeguard"
},
{
"Skill": "hidden_power"
},
{
"Skill": "rain_dance"
},
{
"Skill": "facade"
},
{
"Skill": "poison_jab"
},
{
"Skill": "x_scissor"
},
{
"Skill": "round"
},
{
"Skill": "scald"
},
{
"Skill": "frost_breath"
},
{
"Skill": "confide"
},
{
"Skill": "infestation"
}
],
"SharedSkills": [],
"SecretSkills": [],
"FormName": {
"DefaultText": "Araquanid",
"LocalTexts": {
"ja": "オニシズクモ",
"ko": "깨비물거미",
"zh-hant": "滴蛛霸",
"fr": "Tarenbulle",
"de": "Aranestro",
"es": "Araquanid",
"it": "Araquanid",
"ja-jp": "オニシズクモ",
"zh-hans": "滴蛛霸"
}
},
"Temporary": false,
"PromoteForm": 0,
"Element1": "water",
"Element2": "bug",
"Intrinsic1": "water_bubble",
"Intrinsic2": "none",
"Intrinsic3": "water_absorb",
"LevelSkills": [
{
"Level": 1,
"Skill": "wide_guard"
},
{
"Level": 1,
"Skill": "soak"
},
{
"Level": 1,
"Skill": "bubble"
},
{
"Level": 1,
"Skill": "infestation"
},
{
"Level": 1,
"Skill": "spider_web"
},
{
"Level": 1,
"Skill": "bug_bite"
},
{
"Level": 5,
"Skill": "infestation"
},
{
"Level": 8,
"Skill": "spider_web"
},
{
"Level": 13,
"Skill": "bug_bite"
},
{
"Level": 16,
"Skill": "bubble_beam"
},
{
"Level": 21,
"Skill": "bite"
},
{
"Level": 26,
"Skill": "aqua_ring"
},
{
"Level": 33,
"Skill": "leech_life"
},
{
"Level": 38,
"Skill": "crunch"
},
{
"Level": 45,
"Skill": "lunge"
},
{
"Level": 50,
"Skill": "mirror_coat"
},
{
"Level": 57,
"Skill": "liquidation"
},
{
"Level": 62,
"Skill": "entrainment"
}
]
}
]
}
}