{
"Version": "0.7.20.0",
"Object": {
"$type": "RogueEssence.Data.MonsterData, RogueEssence",
"Name": {
"DefaultText": "Castform",
"LocalTexts": {
"ja": "ポワルン",
"ko": "캐스퐁",
"zh-hant": "飄浮泡泡",
"fr": "Morphéo",
"de": "Formeo",
"es": "Castform",
"it": "Castform",
"ja-jp": "ポワルン",
"zh-hans": "飘浮泡泡"
}
},
"Released": true,
"Comment": "",
"Title": {
"DefaultText": "Weather Pokémon",
"LocalTexts": {
"ja": "てんきポケモン",
"ko": "날씨포켓몬",
"zh-hant": "天氣寶可夢",
"fr": "Pokémon Climat",
"de": "Wetter",
"es": "Pokémon Clima",
"it": "Pokémon Meteo",
"ja-jp": "てんきポケモン",
"zh-hans": "天气宝可梦"
}
},
"IndexNum": 351,
"EXPTable": "medium_fast",
"SkillGroup1": "fairy",
"SkillGroup2": "amorphous",
"JoinRate": -10,
"PromoteFrom": "",
"Promotions": [],
"Forms": [
{
"$type": "PMDC.Data.MonsterFormData, PMDC",
"Released": true,
"Generation": 6,
"GenderlessWeight": 2,
"MaleWeight": 4,
"FemaleWeight": 4,
"BaseHP": 70,
"BaseAtk": 70,
"BaseDef": 70,
"BaseMAtk": 70,
"BaseMDef": 70,
"BaseSpeed": 70,
"ExpYield": 147,
"Height": 0.3,
"Weight": 0.8,
"Personalities": [
0,
1,
2,
3,
8,
9,
14,
16,
24,
26,
29,
30,
31,
36
],
"TeachSkills": [
{
"Skill": "flamethrower"
},
{
"Skill": "ice_beam"
},
{
"Skill": "blizzard"
},
{
"Skill": "solar_beam"
},
{
"Skill": "thunderbolt"
},
{
"Skill": "thunder"
},
{
"Skill": "toxic"
},
{
"Skill": "double_team"
},
{
"Skill": "fire_blast"
},
{
"Skill": "flash"
},
{
"Skill": "rest"
},
{
"Skill": "thief"
},
{
"Skill": "protect"
},
{
"Skill": "sandstorm"
},
{
"Skill": "attract"
},
{
"Skill": "return"
},
{
"Skill": "frustration"
},
{
"Skill": "hidden_power"
},
{
"Skill": "rain_dance"
},
{
"Skill": "sunny_day"
},
{
"Skill": "shadow_ball"
},
{
"Skill": "hail"
},
{
"Skill": "facade"
},
{
"Skill": "secret_power"
},
{
"Skill": "shock_wave"
},
{
"Skill": "water_pulse"
},
{
"Skill": "thunder_wave"
},
{
"Skill": "substitute"
},
{
"Skill": "endure"
},
{
"Skill": "swagger"
},
{
"Skill": "sleep_talk"
},
{
"Skill": "psych_up"
},
{
"Skill": "natural_gift"
},
{
"Skill": "energy_ball"
},
{
"Skill": "avalanche"
},
{
"Skill": "captivate"
},
{
"Skill": "round"
},
{
"Skill": "scald"
},
{
"Skill": "incinerate"
},
{
"Skill": "retaliate"
},
{
"Skill": "work_up"
},
{
"Skill": "confide"
}
],
"SharedSkills": [
{
"Skill": "psych_up"
},
{
"Skill": "future_sight"
},
{
"Skill": "disable"
},
{
"Skill": "amnesia"
},
{
"Skill": "lucky_chant"
},
{
"Skill": "ominous_wind"
},
{
"Skill": "clear_smog"
},
{
"Skill": "hex"
},
{
"Skill": "cosmic_power"
},
{
"Skill": "guard_swap"
},
{
"Skill": "reflect_type"
}
],
"SecretSkills": [
{
"Skill": "body_slam"
},
{
"Skill": "double_edge"
},
{
"Skill": "thunder_wave"
},
{
"Skill": "mimic"
},
{
"Skill": "defense_curl"
},
{
"Skill": "swift"
},
{
"Skill": "substitute"
},
{
"Skill": "snore"
},
{
"Skill": "icy_wind"
},
{
"Skill": "endure"
},
{
"Skill": "swagger"
},
{
"Skill": "sleep_talk"
},
{
"Skill": "psych_up"
},
{
"Skill": "last_resort"
},
{
"Skill": "ominous_wind"
},
{
"Skill": "tailwind"
},
{
"Skill": "shock_wave"
},
{
"Skill": "water_pulse"
}
],
"FormName": {
"DefaultText": "Castform",
"LocalTexts": {
"ja": "ポワルン",
"ko": "캐스퐁",
"zh-hant": "飄浮泡泡",
"fr": "Morphéo",
"de": "Formeo",
"es": "Castform",
"it": "Castform",
"ja-jp": "ポワルン",
"zh-hans": "飘浮泡泡"
}
},
"Temporary": false,
"PromoteForm": 0,
"Element1": "normal",
"Element2": "none",
"Intrinsic1": "forecast",
"Intrinsic2": "none",
"Intrinsic3": "none",
"LevelSkills": [
{
"Level": 1,
"Skill": "tackle"
},
{
"Level": 10,
"Skill": "water_gun"
},
{
"Level": 10,
"Skill": "ember"
},
{
"Level": 10,
"Skill": "powder_snow"
},
{
"Level": 15,
"Skill": "headbutt"
},
{
"Level": 20,
"Skill": "rain_dance"
},
{
"Level": 20,
"Skill": "sunny_day"
},
{
"Level": 20,
"Skill": "hail"
},
{
"Level": 25,
"Skill": "weather_ball"
},
{
"Level": 35,
"Skill": "hydro_pump"
},
{
"Level": 35,
"Skill": "fire_blast"
},
{
"Level": 35,
"Skill": "blizzard"
},
{
"Level": 45,
"Skill": "hurricane"
}
]
},
{
"$type": "PMDC.Data.MonsterFormData, PMDC",
"Released": true,
"Generation": 6,
"GenderlessWeight": 2,
"MaleWeight": 4,
"FemaleWeight": 4,
"BaseHP": 70,
"BaseAtk": 70,
"BaseDef": 70,
"BaseMAtk": 70,
"BaseMDef": 70,
"BaseSpeed": 70,
"ExpYield": 147,
"Height": 0.3,
"Weight": 0.8,
"Personalities": [
0,
1,
2,
3,
8,
9,
14,
16,
24,
26,
29,
30,
31,
36
],
"TeachSkills": [
{
"Skill": "flamethrower"
},
{
"Skill": "ice_beam"
},
{
"Skill": "blizzard"
},
{
"Skill": "solar_beam"
},
{
"Skill": "thunderbolt"
},
{
"Skill": "thunder"
},
{
"Skill": "toxic"
},
{
"Skill": "double_team"
},
{
"Skill": "fire_blast"
},
{
"Skill": "flash"
},
{
"Skill": "rest"
},
{
"Skill": "thief"
},
{
"Skill": "protect"
},
{
"Skill": "sandstorm"
},
{
"Skill": "attract"
},
{
"Skill": "return"
},
{
"Skill": "frustration"
},
{
"Skill": "hidden_power"
},
{
"Skill": "rain_dance"
},
{
"Skill": "sunny_day"
},
{
"Skill": "shadow_ball"
},
{
"Skill": "hail"
},
{
"Skill": "facade"
},
{
"Skill": "secret_power"
},
{
"Skill": "shock_wave"
},
{
"Skill": "water_pulse"
},
{
"Skill": "thunder_wave"
},
{
"Skill": "substitute"
},
{
"Skill": "endure"
},
{
"Skill": "swagger"
},
{
"Skill": "sleep_talk"
},
{
"Skill": "psych_up"
},
{
"Skill": "natural_gift"
},
{
"Skill": "energy_ball"
},
{
"Skill": "avalanche"
},
{
"Skill": "captivate"
},
{
"Skill": "round"
},
{
"Skill": "scald"
},
{
"Skill": "incinerate"
},
{
"Skill": "retaliate"
},
{
"Skill": "work_up"
},
{
"Skill": "confide"
}
],
"SharedSkills": [
{
"Skill": "psych_up"
},
{
"Skill": "future_sight"
},
{
"Skill": "disable"
},
{
"Skill": "amnesia"
},
{
"Skill": "lucky_chant"
},
{
"Skill": "ominous_wind"
},
{
"Skill": "clear_smog"
},
{
"Skill": "hex"
},
{
"Skill": "cosmic_power"
},
{
"Skill": "guard_swap"
},
{
"Skill": "reflect_type"
}
],
"SecretSkills": [
{
"Skill": "body_slam"
},
{
"Skill": "double_edge"
},
{
"Skill": "thunder_wave"
},
{
"Skill": "mimic"
},
{
"Skill": "defense_curl"
},
{
"Skill": "swift"
},
{
"Skill": "substitute"
},
{
"Skill": "snore"
},
{
"Skill": "icy_wind"
},
{
"Skill": "endure"
},
{
"Skill": "swagger"
},
{
"Skill": "sleep_talk"
},
{
"Skill": "psych_up"
},
{
"Skill": "last_resort"
},
{
"Skill": "ominous_wind"
},
{
"Skill": "tailwind"
},
{
"Skill": "shock_wave"
},
{
"Skill": "water_pulse"
}
],
"FormName": {
"DefaultText": "Sunny Castform",
"LocalTexts": {
"ja": "",
"ko": "",
"zh-hant": "",
"fr": "Morphéo Solaire",
"de": "Formeo (Sonne)",
"es": "",
"it": "",
"ja-jp": "",
"zh-hans": ""
}
},
"Temporary": true,
"PromoteForm": 0,
"Element1": "fire",
"Element2": "none",
"Intrinsic1": "forecast",
"Intrinsic2": "none",
"Intrinsic3": "none",
"LevelSkills": [
{
"Level": 1,
"Skill": "tackle"
},
{
"Level": 10,
"Skill": "water_gun"
},
{
"Level": 10,
"Skill": "ember"
},
{
"Level": 10,
"Skill": "powder_snow"
},
{
"Level": 15,
"Skill": "headbutt"
},
{
"Level": 20,
"Skill": "rain_dance"
},
{
"Level": 20,
"Skill": "sunny_day"
},
{
"Level": 20,
"Skill": "hail"
},
{
"Level": 25,
"Skill": "weather_ball"
},
{
"Level": 35,
"Skill": "hydro_pump"
},
{
"Level": 35,
"Skill": "fire_blast"
},
{
"Level": 35,
"Skill": "blizzard"
},
{
"Level": 45,
"Skill": "hurricane"
}
]
},
{
"$type": "PMDC.Data.MonsterFormData, PMDC",
"Released": true,
"Generation": 6,
"GenderlessWeight": 2,
"MaleWeight": 4,
"FemaleWeight": 4,
"BaseHP": 70,
"BaseAtk": 70,
"BaseDef": 70,
"BaseMAtk": 70,
"BaseMDef": 70,
"BaseSpeed": 70,
"ExpYield": 147,
"Height": 0.3,
"Weight": 0.8,
"Personalities": [
0,
1,
2,
3,
8,
9,
14,
16,
24,
26,
29,
30,
31,
36
],
"TeachSkills": [
{
"Skill": "flamethrower"
},
{
"Skill": "ice_beam"
},
{
"Skill": "blizzard"
},
{
"Skill": "solar_beam"
},
{
"Skill": "thunderbolt"
},
{
"Skill": "thunder"
},
{
"Skill": "toxic"
},
{
"Skill": "double_team"
},
{
"Skill": "fire_blast"
},
{
"Skill": "flash"
},
{
"Skill": "rest"
},
{
"Skill": "thief"
},
{
"Skill": "protect"
},
{
"Skill": "sandstorm"
},
{
"Skill": "attract"
},
{
"Skill": "return"
},
{
"Skill": "frustration"
},
{
"Skill": "hidden_power"
},
{
"Skill": "rain_dance"
},
{
"Skill": "sunny_day"
},
{
"Skill": "shadow_ball"
},
{
"Skill": "hail"
},
{
"Skill": "facade"
},
{
"Skill": "secret_power"
},
{
"Skill": "shock_wave"
},
{
"Skill": "water_pulse"
},
{
"Skill": "thunder_wave"
},
{
"Skill": "substitute"
},
{
"Skill": "endure"
},
{
"Skill": "swagger"
},
{
"Skill": "sleep_talk"
},
{
"Skill": "psych_up"
},
{
"Skill": "natural_gift"
},
{
"Skill": "energy_ball"
},
{
"Skill": "avalanche"
},
{
"Skill": "captivate"
},
{
"Skill": "round"
},
{
"Skill": "scald"
},
{
"Skill": "incinerate"
},
{
"Skill": "retaliate"
},
{
"Skill": "work_up"
},
{
"Skill": "confide"
}
],
"SharedSkills": [
{
"Skill": "psych_up"
},
{
"Skill": "future_sight"
},
{
"Skill": "disable"
},
{
"Skill": "amnesia"
},
{
"Skill": "lucky_chant"
},
{
"Skill": "ominous_wind"
},
{
"Skill": "clear_smog"
},
{
"Skill": "hex"
},
{
"Skill": "cosmic_power"
},
{
"Skill": "guard_swap"
},
{
"Skill": "reflect_type"
}
],
"SecretSkills": [
{
"Skill": "body_slam"
},
{
"Skill": "double_edge"
},
{
"Skill": "thunder_wave"
},
{
"Skill": "mimic"
},
{
"Skill": "defense_curl"
},
{
"Skill": "swift"
},
{
"Skill": "substitute"
},
{
"Skill": "snore"
},
{
"Skill": "icy_wind"
},
{
"Skill": "endure"
},
{
"Skill": "swagger"
},
{
"Skill": "sleep_talk"
},
{
"Skill": "psych_up"
},
{
"Skill": "last_resort"
},
{
"Skill": "ominous_wind"
},
{
"Skill": "tailwind"
},
{
"Skill": "shock_wave"
},
{
"Skill": "water_pulse"
}
],
"FormName": {
"DefaultText": "Rainy Castform",
"LocalTexts": {
"ja": "",
"ko": "",
"zh-hant": "",
"fr": "Morphéo Eau de Pluie",
"de": "Formeo (Regen)",
"es": "",
"it": "",
"ja-jp": "",
"zh-hans": ""
}
},
"Temporary": true,
"PromoteForm": 0,
"Element1": "water",
"Element2": "none",
"Intrinsic1": "forecast",
"Intrinsic2": "none",
"Intrinsic3": "none",
"LevelSkills": [
{
"Level": 1,
"Skill": "tackle"
},
{
"Level": 10,
"Skill": "water_gun"
},
{
"Level": 10,
"Skill": "ember"
},
{
"Level": 10,
"Skill": "powder_snow"
},
{
"Level": 15,
"Skill": "headbutt"
},
{
"Level": 20,
"Skill": "rain_dance"
},
{
"Level": 20,
"Skill": "sunny_day"
},
{
"Level": 20,
"Skill": "hail"
},
{
"Level": 25,
"Skill": "weather_ball"
},
{
"Level": 35,
"Skill": "hydro_pump"
},
{
"Level": 35,
"Skill": "fire_blast"
},
{
"Level": 35,
"Skill": "blizzard"
},
{
"Level": 45,
"Skill": "hurricane"
}
]
},
{
"$type": "PMDC.Data.MonsterFormData, PMDC",
"Released": true,
"Generation": 6,
"GenderlessWeight": 2,
"MaleWeight": 4,
"FemaleWeight": 4,
"BaseHP": 70,
"BaseAtk": 70,
"BaseDef": 70,
"BaseMAtk": 70,
"BaseMDef": 70,
"BaseSpeed": 70,
"ExpYield": 147,
"Height": 0.3,
"Weight": 0.8,
"Personalities": [
0,
1,
2,
3,
8,
9,
14,
16,
24,
26,
29,
30,
31,
36
],
"TeachSkills": [
{
"Skill": "flamethrower"
},
{
"Skill": "ice_beam"
},
{
"Skill": "blizzard"
},
{
"Skill": "solar_beam"
},
{
"Skill": "thunderbolt"
},
{
"Skill": "thunder"
},
{
"Skill": "toxic"
},
{
"Skill": "double_team"
},
{
"Skill": "fire_blast"
},
{
"Skill": "flash"
},
{
"Skill": "rest"
},
{
"Skill": "thief"
},
{
"Skill": "protect"
},
{
"Skill": "sandstorm"
},
{
"Skill": "attract"
},
{
"Skill": "return"
},
{
"Skill": "frustration"
},
{
"Skill": "hidden_power"
},
{
"Skill": "rain_dance"
},
{
"Skill": "sunny_day"
},
{
"Skill": "shadow_ball"
},
{
"Skill": "hail"
},
{
"Skill": "facade"
},
{
"Skill": "secret_power"
},
{
"Skill": "shock_wave"
},
{
"Skill": "water_pulse"
},
{
"Skill": "thunder_wave"
},
{
"Skill": "substitute"
},
{
"Skill": "endure"
},
{
"Skill": "swagger"
},
{
"Skill": "sleep_talk"
},
{
"Skill": "psych_up"
},
{
"Skill": "natural_gift"
},
{
"Skill": "energy_ball"
},
{
"Skill": "avalanche"
},
{
"Skill": "captivate"
},
{
"Skill": "round"
},
{
"Skill": "scald"
},
{
"Skill": "incinerate"
},
{
"Skill": "retaliate"
},
{
"Skill": "work_up"
},
{
"Skill": "confide"
}
],
"SharedSkills": [
{
"Skill": "psych_up"
},
{
"Skill": "future_sight"
},
{
"Skill": "disable"
},
{
"Skill": "amnesia"
},
{
"Skill": "lucky_chant"
},
{
"Skill": "ominous_wind"
},
{
"Skill": "clear_smog"
},
{
"Skill": "hex"
},
{
"Skill": "cosmic_power"
},
{
"Skill": "guard_swap"
},
{
"Skill": "reflect_type"
}
],
"SecretSkills": [
{
"Skill": "body_slam"
},
{
"Skill": "double_edge"
},
{
"Skill": "thunder_wave"
},
{
"Skill": "mimic"
},
{
"Skill": "defense_curl"
},
{
"Skill": "swift"
},
{
"Skill": "substitute"
},
{
"Skill": "snore"
},
{
"Skill": "icy_wind"
},
{
"Skill": "endure"
},
{
"Skill": "swagger"
},
{
"Skill": "sleep_talk"
},
{
"Skill": "psych_up"
},
{
"Skill": "last_resort"
},
{
"Skill": "ominous_wind"
},
{
"Skill": "tailwind"
},
{
"Skill": "shock_wave"
},
{
"Skill": "water_pulse"
}
],
"FormName": {
"DefaultText": "Snowy Castform",
"LocalTexts": {
"ja": "",
"ko": "",
"zh-hant": "",
"fr": "Morphéo Blizzard",
"de": "Formeo (Schnee)",
"es": "",
"it": "",
"ja-jp": "",
"zh-hans": ""
}
},
"Temporary": true,
"PromoteForm": 0,
"Element1": "ice",
"Element2": "none",
"Intrinsic1": "forecast",
"Intrinsic2": "none",
"Intrinsic3": "none",
"LevelSkills": [
{
"Level": 1,
"Skill": "tackle"
},
{
"Level": 10,
"Skill": "water_gun"
},
{
"Level": 10,
"Skill": "ember"
},
{
"Level": 10,
"Skill": "powder_snow"
},
{
"Level": 15,
"Skill": "headbutt"
},
{
"Level": 20,
"Skill": "rain_dance"
},
{
"Level": 20,
"Skill": "sunny_day"
},
{
"Level": 20,
"Skill": "hail"
},
{
"Level": 25,
"Skill": "weather_ball"
},
{
"Level": 35,
"Skill": "hydro_pump"
},
{
"Level": 35,
"Skill": "fire_blast"
},
{
"Level": 35,
"Skill": "blizzard"
},
{
"Level": 45,
"Skill": "hurricane"
}
]
}
]
}
}