{
"Version": "0.6.0.0",
"Object": {
"$type": "RogueEssence.Data.MonsterData, RogueEssence",
"Name": {
"DefaultText": "Cursola",
"LocalTexts": {
"ja": "サニゴーン",
"ko": "산호르곤",
"zh-hant": "魔靈珊瑚",
"fr": "Corayôme",
"de": "Gorgasonn",
"es": "Cursola",
"it": "Cursola",
"ja-jp": "サニゴーン",
"zh-hans": "魔灵珊瑚"
}
},
"Released": true,
"Comment": "",
"Title": {
"DefaultText": "Coral Pokémon",
"LocalTexts": {
"ja": "さんごポケモン",
"ko": "산호포켓몬",
"zh-hant": "珊瑚寶可夢",
"fr": "Pokémon Corail",
"de": "Koralle",
"es": "Pokémon Coral",
"it": "Pokémon Corallo",
"ja-jp": "さんごポケモン",
"zh-hans": "珊瑚宝可梦"
}
},
"IndexNum": 864,
"EXPTable": "fast",
"SkillGroup1": "undiscovered",
"SkillGroup2": "undiscovered",
"JoinRate": -33,
"PromoteFrom": "corsola",
"Promotions": [],
"Forms": [
{
"$type": "PMDC.Data.MonsterFormData, PMDC",
"Released": true,
"Generation": 8,
"Ratio": 0,
"GenderlessWeight": 2,
"MaleWeight": 2,
"FemaleWeight": 6,
"BaseHP": 60,
"BaseAtk": 95,
"BaseDef": 50,
"BaseMAtk": 145,
"BaseMDef": 130,
"BaseSpeed": 30,
"ExpYield": 179,
"Height": 1.0,
"Weight": 0.4,
"Personalities": [
31
],
"TeachSkills": [],
"SharedSkills": [],
"SecretSkills": [],
"FormName": {
"DefaultText": "Cursola",
"LocalTexts": {
"ja": "サニゴーン",
"ko": "산호르곤",
"zh-hant": "魔靈珊瑚",
"fr": "Corayôme",
"de": "Gorgasonn",
"es": "Cursola",
"it": "Cursola",
"ja-jp": "サニゴーン",
"zh-hans": "魔灵珊瑚"
}
},
"Temporary": false,
"Element1": "ghost",
"Element2": "none",
"Intrinsic1": "weak_armor",
"Intrinsic2": "none",
"Intrinsic3": "perish_body",
"LevelSkills": []
}
]
}
}