{
"Version": "0.7.20.0",
"Object": {
"$type": "RogueEssence.Data.MonsterData, RogueEssence",
"Name": {
"DefaultText": "Cyndaquil",
"LocalTexts": {
"ja": "ヒノアラシ",
"ko": "브케인",
"zh-hant": "火球鼠",
"fr": "Héricendre",
"de": "Feurigel",
"es": "Cyndaquil",
"it": "Cyndaquil",
"ja-jp": "ヒノアラシ",
"zh-hans": "火球鼠"
}
},
"Released": true,
"Comment": "",
"Title": {
"DefaultText": "Fire Mouse Pokémon",
"LocalTexts": {
"ja": "ひねずみポケモン",
"ko": "불쥐포켓몬",
"zh-hant": "火鼠寶可夢",
"fr": "Pokémon Souris Feu",
"de": "Feuermaus",
"es": "Pokémon Ratón Fuego",
"it": "Pokémon Fuocotopo",
"ja-jp": "ひねずみポケモン",
"zh-hans": "火鼠宝可梦"
}
},
"IndexNum": 155,
"EXPTable": "medium_slow",
"SkillGroup1": "field",
"SkillGroup2": "",
"JoinRate": 19,
"PromoteFrom": "",
"Promotions": [
{
"Result": "quilava",
"Details": [
{
"$type": "PMDC.Data.EvoLevel, PMDC",
"Level": 14
}
]
}
],
"Forms": [
{
"$type": "PMDC.Data.MonsterFormData, PMDC",
"Released": true,
"Generation": 6,
"GenderlessWeight": 2,
"MaleWeight": 7,
"FemaleWeight": 1,
"BaseHP": 39,
"BaseAtk": 52,
"BaseDef": 43,
"BaseMAtk": 60,
"BaseMDef": 50,
"BaseSpeed": 65,
"ExpYield": 62,
"Height": 0.5,
"Weight": 7.9,
"Personalities": [
0,
1,
2,
3,
8,
9,
10,
11,
16,
24,
30,
31,
36
],
"TeachSkills": [
{
"Skill": "cut"
},
{
"Skill": "flamethrower"
},
{
"Skill": "dig"
},
{
"Skill": "toxic"
},
{
"Skill": "double_team"
},
{
"Skill": "fire_blast"
},
{
"Skill": "rest"
},
{
"Skill": "protect"
},
{
"Skill": "attract"
},
{
"Skill": "return"
},
{
"Skill": "frustration"
},
{
"Skill": "hidden_power"
},
{
"Skill": "sunny_day"
},
{
"Skill": "facade"
},
{
"Skill": "secret_power"
},
{
"Skill": "overheat"
},
{
"Skill": "aerial_ace"
},
{
"Skill": "substitute"
},
{
"Skill": "endure"
},
{
"Skill": "swagger"
},
{
"Skill": "sleep_talk"
},
{
"Skill": "will_o_wisp"
},
{
"Skill": "natural_gift"
},
{
"Skill": "captivate"
},
{
"Skill": "flame_charge"
},
{
"Skill": "round"
},
{
"Skill": "incinerate"
},
{
"Skill": "wild_charge"
},
{
"Skill": "nature_power"
},
{
"Skill": "confide"
}
],
"SharedSkills": [
{
"Skill": "thrash"
},
{
"Skill": "quick_attack"
},
{
"Skill": "fury_swipes"
},
{
"Skill": "reversal"
},
{
"Skill": "foresight"
},
{
"Skill": "crush_claw"
},
{
"Skill": "howl"
},
{
"Skill": "covet"
},
{
"Skill": "double_kick"
},
{
"Skill": "double_edge"
},
{
"Skill": "flare_blitz"
},
{
"Skill": "extrasensory"
},
{
"Skill": "nature_power"
},
{
"Skill": "flame_burst"
}
],
"SecretSkills": [
{
"Skill": "body_slam"
},
{
"Skill": "double_edge"
},
{
"Skill": "mimic"
},
{
"Skill": "defense_curl"
},
{
"Skill": "swift"
},
{
"Skill": "substitute"
},
{
"Skill": "snore"
},
{
"Skill": "mud_slap"
},
{
"Skill": "endure"
},
{
"Skill": "rollout"
},
{
"Skill": "swagger"
},
{
"Skill": "sleep_talk"
},
{
"Skill": "heat_wave"
},
{
"Skill": "headbutt"
},
{
"Skill": "fire_pledge"
},
{
"Skill": "covet"
}
],
"FormName": {
"DefaultText": "Cyndaquil",
"LocalTexts": {
"ja": "ヒノアラシ",
"ko": "브케인",
"zh-hant": "火球鼠",
"fr": "Héricendre",
"de": "Feurigel",
"es": "Cyndaquil",
"it": "Cyndaquil",
"ja-jp": "ヒノアラシ",
"zh-hans": "火球鼠"
}
},
"Temporary": false,
"PromoteForm": 0,
"Element1": "fire",
"Element2": "none",
"Intrinsic1": "blaze",
"Intrinsic2": "none",
"Intrinsic3": "flash_fire",
"LevelSkills": [
{
"Level": 1,
"Skill": "tackle"
},
{
"Level": 1,
"Skill": "leer"
},
{
"Level": 6,
"Skill": "smokescreen"
},
{
"Level": 10,
"Skill": "ember"
},
{
"Level": 13,
"Skill": "quick_attack"
},
{
"Level": 19,
"Skill": "flame_wheel"
},
{
"Level": 22,
"Skill": "defense_curl"
},
{
"Level": 28,
"Skill": "flame_charge"
},
{
"Level": 31,
"Skill": "swift"
},
{
"Level": 37,
"Skill": "lava_plume"
},
{
"Level": 40,
"Skill": "flamethrower"
},
{
"Level": 46,
"Skill": "inferno"
},
{
"Level": 49,
"Skill": "rollout"
},
{
"Level": 55,
"Skill": "double_edge"
},
{
"Level": 58,
"Skill": "eruption"
}
]
}
]
}
}