{
"Version": "0.7.20.0",
"Object": {
"$type": "RogueEssence.Data.MonsterData, RogueEssence",
"Name": {
"DefaultText": "Floatzel",
"LocalTexts": {
"ja": "フローゼル",
"ko": "플로젤",
"zh-hant": "浮潛鼬",
"fr": "Mustéflott",
"de": "Bojelin",
"es": "Floatzel",
"it": "Floatzel",
"ja-jp": "フローゼル",
"zh-hans": "浮潜鼬"
}
},
"Released": true,
"Comment": "",
"Title": {
"DefaultText": "Sea Weasel Pokémon",
"LocalTexts": {
"ja": "うみイタチポケモン",
"ko": "바다족제비포켓몬",
"zh-hant": "海鼬寶可夢",
"fr": "Pokémon Aquabelette",
"de": "Meereswiesel",
"es": "Pokémon Nutria Mar.",
"it": "Pokémon Maridonnola",
"ja-jp": "うみイタチポケモン",
"zh-hans": "海鼬宝可梦"
}
},
"IndexNum": 419,
"EXPTable": "medium_fast",
"SkillGroup1": "water_1",
"SkillGroup2": "field",
"JoinRate": -25,
"PromoteFrom": "buizel",
"Promotions": [],
"Forms": [
{
"$type": "PMDC.Data.MonsterFormData, PMDC",
"Released": true,
"Generation": 6,
"GenderlessWeight": 2,
"MaleWeight": 4,
"FemaleWeight": 4,
"BaseHP": 85,
"BaseAtk": 105,
"BaseDef": 55,
"BaseMAtk": 85,
"BaseMDef": 50,
"BaseSpeed": 115,
"ExpYield": 173,
"Height": 1.1,
"Weight": 33.5,
"Personalities": [
0,
1,
2,
3,
7,
9,
10,
11,
12,
13,
14,
15,
16,
29,
30,
31,
36
],
"TeachSkills": [
{
"Skill": "roar"
},
{
"Skill": "surf"
},
{
"Skill": "ice_beam"
},
{
"Skill": "blizzard"
},
{
"Skill": "hyper_beam"
},
{
"Skill": "strength"
},
{
"Skill": "dig"
},
{
"Skill": "toxic"
},
{
"Skill": "double_team"
},
{
"Skill": "waterfall"
},
{
"Skill": "rest"
},
{
"Skill": "substitute"
},
{
"Skill": "protect"
},
{
"Skill": "endure"
},
{
"Skill": "swagger"
},
{
"Skill": "attract"
},
{
"Skill": "sleep_talk"
},
{
"Skill": "return"
},
{
"Skill": "frustration"
},
{
"Skill": "iron_tail"
},
{
"Skill": "hidden_power"
},
{
"Skill": "rain_dance"
},
{
"Skill": "rock_smash"
},
{
"Skill": "hail"
},
{
"Skill": "torment"
},
{
"Skill": "facade"
},
{
"Skill": "focus_punch"
},
{
"Skill": "taunt"
},
{
"Skill": "brick_break"
},
{
"Skill": "secret_power"
},
{
"Skill": "rock_tomb"
},
{
"Skill": "bulk_up"
},
{
"Skill": "water_pulse"
},
{
"Skill": "brine"
},
{
"Skill": "natural_gift"
},
{
"Skill": "payback"
},
{
"Skill": "focus_blast"
},
{
"Skill": "giga_impact"
},
{
"Skill": "captivate"
},
{
"Skill": "whirlpool"
},
{
"Skill": "dive"
},
{
"Skill": "round"
},
{
"Skill": "echoed_voice"
},
{
"Skill": "scald"
},
{
"Skill": "confide"
},
{
"Skill": "power_up_punch"
}
],
"SharedSkills": [],
"SecretSkills": [
{
"Skill": "ice_punch"
},
{
"Skill": "swift"
},
{
"Skill": "snore"
},
{
"Skill": "mud_slap"
},
{
"Skill": "icy_wind"
},
{
"Skill": "dive"
},
{
"Skill": "aqua_tail"
},
{
"Skill": "headbutt"
},
{
"Skill": "low_kick"
},
{
"Skill": "sleep_talk"
},
{
"Skill": "iron_tail"
},
{
"Skill": "focus_punch"
},
{
"Skill": "water_pulse"
}
],
"FormName": {
"DefaultText": "Floatzel",
"LocalTexts": {
"ja": "フローゼル",
"ko": "플로젤",
"zh-hant": "浮潛鼬",
"fr": "Mustéflott",
"de": "Bojelin",
"es": "Floatzel",
"it": "Floatzel",
"ja-jp": "フローゼル",
"zh-hans": "浮潜鼬"
}
},
"Temporary": false,
"PromoteForm": 0,
"Element1": "water",
"Element2": "none",
"Intrinsic1": "swift_swim",
"Intrinsic2": "none",
"Intrinsic3": "water_veil",
"LevelSkills": [
{
"Level": 1,
"Skill": "ice_fang"
},
{
"Level": 1,
"Skill": "crunch"
},
{
"Level": 1,
"Skill": "sonic_boom"
},
{
"Level": 1,
"Skill": "growl"
},
{
"Level": 1,
"Skill": "water_sport"
},
{
"Level": 1,
"Skill": "quick_attack"
},
{
"Level": 4,
"Skill": "growl"
},
{
"Level": 7,
"Skill": "water_sport"
},
{
"Level": 11,
"Skill": "quick_attack"
},
{
"Level": 15,
"Skill": "water_gun"
},
{
"Level": 18,
"Skill": "pursuit"
},
{
"Level": 21,
"Skill": "swift"
},
{
"Level": 24,
"Skill": "aqua_jet"
},
{
"Level": 29,
"Skill": "double_hit"
},
{
"Level": 35,
"Skill": "whirlpool"
},
{
"Level": 41,
"Skill": "razor_wind"
},
{
"Level": 46,
"Skill": "aqua_tail"
},
{
"Level": 51,
"Skill": "agility"
},
{
"Level": 57,
"Skill": "hydro_pump"
}
]
}
]
}
}