{
"Version": "0.7.20.0",
"Object": {
"$type": "RogueEssence.Data.MonsterData, RogueEssence",
"Name": {
"DefaultText": "Liepard",
"LocalTexts": {
"ja": "レパルダス",
"ko": "레파르다스",
"zh-hant": "酷豹",
"fr": "Léopardus",
"de": "Kleoparda",
"es": "Liepard",
"it": "Liepard",
"ja-jp": "レパルダス",
"zh-hans": "酷豹"
}
},
"Released": true,
"Comment": "",
"Title": {
"DefaultText": "Cruel Pokémon",
"LocalTexts": {
"ja": "れいこくポケモン",
"ko": "냉혹포켓몬",
"zh-hant": "冷酷寶可夢",
"fr": "Pokémon Implacable",
"de": "Gefühlskälte-Pokémon",
"es": "Pokémon Calculador",
"it": "Pokémon Sanguefreddo",
"ja-jp": "れいこくポケモン",
"zh-hans": "冷酷宝可梦"
}
},
"IndexNum": 510,
"EXPTable": "medium_fast",
"SkillGroup1": "field",
"SkillGroup2": "",
"JoinRate": -15,
"PromoteFrom": "purrloin",
"Promotions": [],
"Forms": [
{
"$type": "PMDC.Data.MonsterFormData, PMDC",
"Released": true,
"Generation": 6,
"GenderlessWeight": 2,
"MaleWeight": 4,
"FemaleWeight": 4,
"BaseHP": 64,
"BaseAtk": 88,
"BaseDef": 50,
"BaseMAtk": 88,
"BaseMDef": 50,
"BaseSpeed": 106,
"ExpYield": 156,
"Height": 1.1,
"Weight": 37.5,
"Personalities": [
31
],
"TeachSkills": [
{
"Skill": "cut"
},
{
"Skill": "hyper_beam"
},
{
"Skill": "thunder_wave"
},
{
"Skill": "toxic"
},
{
"Skill": "double_team"
},
{
"Skill": "dream_eater"
},
{
"Skill": "rest"
},
{
"Skill": "substitute"
},
{
"Skill": "thief"
},
{
"Skill": "protect"
},
{
"Skill": "swagger"
},
{
"Skill": "attract"
},
{
"Skill": "return"
},
{
"Skill": "frustration"
},
{
"Skill": "hidden_power"
},
{
"Skill": "rain_dance"
},
{
"Skill": "sunny_day"
},
{
"Skill": "psych_up"
},
{
"Skill": "shadow_ball"
},
{
"Skill": "rock_smash"
},
{
"Skill": "torment"
},
{
"Skill": "facade"
},
{
"Skill": "taunt"
},
{
"Skill": "aerial_ace"
},
{
"Skill": "payback"
},
{
"Skill": "embargo"
},
{
"Skill": "giga_impact"
},
{
"Skill": "shadow_claw"
},
{
"Skill": "grass_knot"
},
{
"Skill": "hone_claws"
},
{
"Skill": "round"
},
{
"Skill": "echoed_voice"
},
{
"Skill": "snarl"
},
{
"Skill": "u_turn"
},
{
"Skill": "sleep_talk"
},
{
"Skill": "dark_pulse"
},
{
"Skill": "confide"
},
{
"Skill": "secret_power"
}
],
"SharedSkills": [],
"SecretSkills": [
{
"Skill": "snore"
},
{
"Skill": "spite"
},
{
"Skill": "sleep_talk"
},
{
"Skill": "iron_tail"
},
{
"Skill": "trick"
},
{
"Skill": "role_play"
},
{
"Skill": "knock_off"
},
{
"Skill": "snatch"
},
{
"Skill": "hyper_voice"
},
{
"Skill": "covet"
},
{
"Skill": "dark_pulse"
},
{
"Skill": "seed_bomb"
},
{
"Skill": "gunk_shot"
},
{
"Skill": "foul_play"
}
],
"FormName": {
"DefaultText": "Liepard",
"LocalTexts": {
"ja": "レパルダス",
"ko": "레파르다스",
"zh-hant": "酷豹",
"fr": "Léopardus",
"de": "Kleoparda",
"es": "Liepard",
"it": "Liepard",
"ja-jp": "レパルダス",
"zh-hans": "酷豹"
}
},
"Temporary": false,
"PromoteForm": 0,
"Element1": "dark",
"Element2": "none",
"Intrinsic1": "limber",
"Intrinsic2": "unburden",
"Intrinsic3": "prankster",
"LevelSkills": [
{
"Level": 1,
"Skill": "scratch"
},
{
"Level": 1,
"Skill": "growl"
},
{
"Level": 1,
"Skill": "assist"
},
{
"Level": 1,
"Skill": "sand_attack"
},
{
"Level": 3,
"Skill": "growl"
},
{
"Level": 6,
"Skill": "assist"
},
{
"Level": 10,
"Skill": "sand_attack"
},
{
"Level": 12,
"Skill": "fury_swipes"
},
{
"Level": 15,
"Skill": "pursuit"
},
{
"Level": 19,
"Skill": "torment"
},
{
"Level": 22,
"Skill": "fake_out"
},
{
"Level": 26,
"Skill": "hone_claws"
},
{
"Level": 31,
"Skill": "assurance"
},
{
"Level": 34,
"Skill": "slash"
},
{
"Level": 38,
"Skill": "taunt"
},
{
"Level": 43,
"Skill": "night_slash"
},
{
"Level": 47,
"Skill": "snatch"
},
{
"Level": 50,
"Skill": "nasty_plot"
},
{
"Level": 55,
"Skill": "sucker_punch"
},
{
"Level": 58,
"Skill": "play_rough"
}
]
}
]
}
}