{
"Version": "0.7.20.0",
"Object": {
"$type": "RogueEssence.Data.MonsterData, RogueEssence",
"Name": {
"DefaultText": "Oinkologne",
"LocalTexts": {
"ja": "パフュートン",
"ko": "퍼퓨돈",
"zh-hant": "飄香豚",
"fr": "Fragroin",
"de": "Fragrunz",
"ja-jp": "パフュートン",
"zh-hans": "飘香豚"
}
},
"Released": false,
"Comment": "",
"Title": {
"DefaultText": "Hog Pokémon",
"LocalTexts": {
"ja": "ぶたポケモン",
"ko": "",
"zh-hant": "豬寶可夢",
"fr": "",
"de": "Schwein",
"ja-jp": "",
"zh-hans": "猪宝可梦"
}
},
"IndexNum": 916,
"EXPTable": "medium_fast",
"SkillGroup1": "field",
"SkillGroup2": "",
"JoinRate": -15,
"PromoteFrom": "lechonk",
"Promotions": [],
"Forms": [
{
"$type": "PMDC.Data.MonsterFormData, PMDC",
"Released": false,
"Generation": 9,
"GenderlessWeight": 2,
"MaleWeight": 8,
"FemaleWeight": 0,
"BaseHP": 110,
"BaseAtk": 100,
"BaseDef": 75,
"BaseMAtk": 59,
"BaseMDef": 80,
"BaseSpeed": 65,
"ExpYield": 122,
"Height": 1.0,
"Weight": 120.0,
"Personalities": [
31
],
"TeachSkills": [
{
"Skill": "body_slam"
},
{
"Skill": "take_down"
},
{
"Skill": "hyper_beam"
},
{
"Skill": "dig"
},
{
"Skill": "rest"
},
{
"Skill": "substitute"
},
{
"Skill": "thief"
},
{
"Skill": "protect"
},
{
"Skill": "mud_slap"
},
{
"Skill": "endure"
},
{
"Skill": "sleep_talk"
},
{
"Skill": "rain_dance"
},
{
"Skill": "sunny_day"
},
{
"Skill": "facade"
},
{
"Skill": "helping_hand"
},
{
"Skill": "hyper_voice"
},
{
"Skill": "bullet_seed"
},
{
"Skill": "mud_shot"
},
{
"Skill": "seed_bomb"
},
{
"Skill": "energy_ball"
},
{
"Skill": "earth_power"
},
{
"Skill": "giga_impact"
},
{
"Skill": "zen_headbutt"
},
{
"Skill": "iron_head"
},
{
"Skill": "bulldoze"
},
{
"Skill": "disarming_voice"
},
{
"Skill": "play_rough"
},
{
"Skill": "stomping_tantrum"
},
{
"Skill": "body_press"
},
{
"Skill": "tera_blast"
},
{
"Skill": "trailblaze"
},
{
"Skill": "chilling_water"
}
],
"SharedSkills": [],
"SecretSkills": [],
"FormName": {
"DefaultText": "Oinkologne",
"LocalTexts": {
"ja": "パフュートン",
"ko": "퍼퓨돈",
"zh-hant": "飄香豚",
"fr": "Fragroin",
"de": "Fragrunz",
"ja-jp": "パフュートン",
"zh-hans": "飘香豚"
}
},
"Temporary": false,
"PromoteForm": 0,
"Element1": "normal",
"Element2": "none",
"Intrinsic1": "lingering_aroma",
"Intrinsic2": "gluttony",
"Intrinsic3": "thick_fat",
"LevelSkills": [
{
"Level": 1,
"Skill": "tackle"
},
{
"Level": 1,
"Skill": "tail_whip"
},
{
"Level": 5,
"Skill": "disarming_voice"
},
{
"Level": 8,
"Skill": "echoed_voice"
},
{
"Level": 12,
"Skill": "mud_shot"
},
{
"Level": 15,
"Skill": "covet"
},
{
"Level": 17,
"Skill": "dig"
},
{
"Level": 23,
"Skill": "headbutt"
},
{
"Level": 26,
"Skill": "take_down"
},
{
"Level": 27,
"Skill": "yawn"
},
{
"Level": 34,
"Skill": "work_up"
},
{
"Level": 38,
"Skill": "uproar"
},
{
"Level": 42,
"Skill": "double_edge"
},
{
"Level": 48,
"Skill": "earth_power"
},
{
"Level": 54,
"Skill": "belch"
}
]
},
{
"$type": "PMDC.Data.MonsterFormData, PMDC",
"Released": false,
"Generation": 9,
"GenderlessWeight": 2,
"MaleWeight": 8,
"FemaleWeight": 0,
"BaseHP": 115,
"BaseAtk": 90,
"BaseDef": 70,
"BaseMAtk": 59,
"BaseMDef": 90,
"BaseSpeed": 65,
"ExpYield": 122,
"Height": 1.0,
"Weight": 120.0,
"Personalities": [
31
],
"TeachSkills": [
{
"Skill": "body_slam"
},
{
"Skill": "take_down"
},
{
"Skill": "hyper_beam"
},
{
"Skill": "dig"
},
{
"Skill": "rest"
},
{
"Skill": "substitute"
},
{
"Skill": "thief"
},
{
"Skill": "protect"
},
{
"Skill": "mud_slap"
},
{
"Skill": "endure"
},
{
"Skill": "sleep_talk"
},
{
"Skill": "rain_dance"
},
{
"Skill": "sunny_day"
},
{
"Skill": "facade"
},
{
"Skill": "helping_hand"
},
{
"Skill": "hyper_voice"
},
{
"Skill": "bullet_seed"
},
{
"Skill": "mud_shot"
},
{
"Skill": "seed_bomb"
},
{
"Skill": "energy_ball"
},
{
"Skill": "earth_power"
},
{
"Skill": "giga_impact"
},
{
"Skill": "zen_headbutt"
},
{
"Skill": "iron_head"
},
{
"Skill": "bulldoze"
},
{
"Skill": "disarming_voice"
},
{
"Skill": "play_rough"
},
{
"Skill": "stomping_tantrum"
},
{
"Skill": "body_press"
},
{
"Skill": "tera_blast"
},
{
"Skill": "trailblaze"
},
{
"Skill": "chilling_water"
}
],
"SharedSkills": [],
"SecretSkills": [],
"FormName": {
"DefaultText": "Oinkologne",
"LocalTexts": {
"ja": "パフュートン",
"ko": "퍼퓨돈",
"zh-hant": "飄香豚",
"fr": "Fragroin",
"de": "Fragrunz",
"ja-jp": "パフュートン",
"zh-hans": "飘香豚"
}
},
"Temporary": false,
"PromoteForm": 0,
"Element1": "normal",
"Element2": "none",
"Intrinsic1": "aroma_veil",
"Intrinsic2": "gluttony",
"Intrinsic3": "thick_fat",
"LevelSkills": [
{
"Level": 1,
"Skill": "tackle"
},
{
"Level": 1,
"Skill": "tail_whip"
},
{
"Level": 3,
"Skill": "disarming_voice"
},
{
"Level": 6,
"Skill": "echoed_voice"
},
{
"Level": 9,
"Skill": "mud_shot"
},
{
"Level": 12,
"Skill": "covet"
},
{
"Level": 15,
"Skill": "dig"
},
{
"Level": 17,
"Skill": "headbutt"
},
{
"Level": 23,
"Skill": "yawn"
},
{
"Level": 28,
"Skill": "take_down"
},
{
"Level": 30,
"Skill": "work_up"
},
{
"Level": 34,
"Skill": "uproar"
},
{
"Level": 39,
"Skill": "double_edge"
},
{
"Level": 45,
"Skill": "earth_power"
},
{
"Level": 51,
"Skill": "belch"
}
]
}
]
}
}