{
"Version": "0.7.20.0",
"Object": {
"$type": "RogueEssence.Data.MonsterData, RogueEssence",
"Name": {
"DefaultText": "Zeraora",
"LocalTexts": {
"ja": "ゼラオラ",
"ko": "제라오라",
"zh-hant": "捷拉奧拉",
"fr": "Zeraora",
"de": "Zeraora",
"es": "Zeraora",
"it": "Zeraora",
"ja-jp": "ゼラオラ",
"zh-hans": "捷拉奥拉"
}
},
"Released": true,
"Comment": "",
"Title": {
"DefaultText": "Thunderclap Pokémon",
"LocalTexts": {
"ja": "じんらいポケモン",
"ko": "신뢰포켓몬",
"zh-hant": "奔雷寶可夢",
"fr": "Pokémon Vif Éclair",
"de": "Blitzsturm-Pokémon",
"es": "Pokémon Fulgor",
"it": "Pokémon Fulmirapido",
"ja-jp": "じんらいポケモン",
"zh-hans": "奔雷宝可梦"
}
},
"IndexNum": 807,
"EXPTable": "slow",
"SkillGroup1": "undiscovered",
"SkillGroup2": "",
"JoinRate": -25,
"PromoteFrom": "",
"Promotions": [],
"Forms": [
{
"$type": "PMDC.Data.MonsterFormData, PMDC",
"Released": true,
"Generation": 7,
"GenderlessWeight": 8,
"MaleWeight": 1,
"FemaleWeight": 1,
"BaseHP": 88,
"BaseAtk": 112,
"BaseDef": 75,
"BaseMAtk": 102,
"BaseMDef": 80,
"BaseSpeed": 143,
"ExpYield": 300,
"Height": 1.5,
"Weight": 44.5,
"Personalities": [
4,
5
],
"TeachSkills": [
{
"Skill": "thunderbolt"
},
{
"Skill": "thunder_wave"
},
{
"Skill": "thunder"
},
{
"Skill": "toxic"
},
{
"Skill": "double_team"
},
{
"Skill": "rest"
},
{
"Skill": "substitute"
},
{
"Skill": "protect"
},
{
"Skill": "false_swipe"
},
{
"Skill": "sleep_talk"
},
{
"Skill": "return"
},
{
"Skill": "frustration"
},
{
"Skill": "hidden_power"
},
{
"Skill": "facade"
},
{
"Skill": "taunt"
},
{
"Skill": "brick_break"
},
{
"Skill": "aerial_ace"
},
{
"Skill": "bulk_up"
},
{
"Skill": "calm_mind"
},
{
"Skill": "fling"
},
{
"Skill": "focus_blast"
},
{
"Skill": "giga_impact"
},
{
"Skill": "grass_knot"
},
{
"Skill": "low_sweep"
},
{
"Skill": "round"
},
{
"Skill": "echoed_voice"
},
{
"Skill": "acrobatics"
},
{
"Skill": "volt_switch"
},
{
"Skill": "work_up"
},
{
"Skill": "wild_charge"
},
{
"Skill": "snarl"
},
{
"Skill": "confide"
},
{
"Skill": "brutal_swing"
}
],
"SharedSkills": [],
"SecretSkills": [
{
"Skill": "fire_punch"
},
{
"Skill": "thunder_punch"
},
{
"Skill": "low_kick"
},
{
"Skill": "snore"
},
{
"Skill": "outrage"
},
{
"Skill": "iron_tail"
},
{
"Skill": "focus_punch"
},
{
"Skill": "superpower"
},
{
"Skill": "knock_off"
},
{
"Skill": "endeavor"
},
{
"Skill": "snatch"
},
{
"Skill": "bounce"
},
{
"Skill": "shock_wave"
},
{
"Skill": "drain_punch"
},
{
"Skill": "electroweb"
},
{
"Skill": "dual_chop"
},
{
"Skill": "laser_focus"
},
{
"Skill": "throat_chop"
}
],
"FormName": {
"DefaultText": "Zeraora",
"LocalTexts": {
"ja": "ゼラオラ",
"ko": "제라오라",
"zh-hant": "捷拉奧拉",
"fr": "Zeraora",
"de": "Zeraora",
"es": "Zeraora",
"it": "Zeraora",
"ja-jp": "ゼラオラ",
"zh-hans": "捷拉奥拉"
}
},
"Temporary": false,
"PromoteForm": 0,
"Element1": "electric",
"Element2": "none",
"Intrinsic1": "volt_absorb",
"Intrinsic2": "none",
"Intrinsic3": "none",
"LevelSkills": [
{
"Level": 1,
"Skill": "scratch"
},
{
"Level": 1,
"Skill": "spark"
},
{
"Level": 5,
"Skill": "hone_claws"
},
{
"Level": 8,
"Skill": "quick_attack"
},
{
"Level": 12,
"Skill": "fury_swipes"
},
{
"Level": 15,
"Skill": "volt_switch"
},
{
"Level": 19,
"Skill": "snarl"
},
{
"Level": 22,
"Skill": "fake_out"
},
{
"Level": 26,
"Skill": "charge"
},
{
"Level": 29,
"Skill": "thunder_punch"
},
{
"Level": 33,
"Skill": "slash"
},
{
"Level": 36,
"Skill": "wild_charge"
},
{
"Level": 40,
"Skill": "quick_guard"
},
{
"Level": 43,
"Skill": "plasma_fists"
},
{
"Level": 47,
"Skill": "close_combat"
},
{
"Level": 50,
"Skill": "discharge"
}
]
}
]
}
}